tests/__init__.py
tests/conftest.py
tests/test_bool.py
tests/test_bytes.py
tests/test_class.py
tests/test_complex.py
tests/test_dict.py
tests/test_extensions.py
tests/test_float.py
tests/test_int.py
tests/test_list.py
tests/test_nested_types.py
tests/test_none.py
tests/test_protocol_version.py
tests/test_range.py
tests/test_set.py
tests/test_string.py
tests/test_tuple.py
urine/__init__.py
urine/decoder.py
urine/encoder.py
urine/extensions.py
urine/types.py
urine-0.1.0.dist-info/LICENSE
urine-0.1.0.dist-info/METADATA
urine-0.1.0.dist-info/WHEEL
urine-0.1.0.dist-info/top_level.txt
urine-0.1.0.dist-info/RECORD
