Metadata-Version: 2.1
Name: urine
Version: 0.1.0
Summary: Simple and secure binary serialization for Python objects
Home-page: https://github.com/chrstnkln/urine
Author: Christian Klein
Author-email: klein_chris@outlook.com
License: UNKNOWN
Platform: UNKNOWN
Classifier: Development Status :: 4 - Beta
Classifier: Intended Audience :: Developers
Classifier: License :: OSI Approved :: MIT License
Classifier: Operating System :: OS Independent
Classifier: Programming Language :: Python
Classifier: Programming Language :: Python :: 3
Classifier: Programming Language :: Python :: 3 :: Only
Classifier: Programming Language :: Python :: 3.6
Classifier: Programming Language :: Python :: 3.7
Classifier: Programming Language :: Python :: 3.8
Classifier: Programming Language :: Python :: 3.9
Classifier: Programming Language :: Python :: 3.10
Requires-Python: >=3.6
Provides-Extra: dev
Requires-Dist: pytest (>=7.0.0) ; extra == 'dev'
Requires-Dist: pytest-cov (>=3.0.0) ; extra == 'dev'
Requires-Dist: flake8 (>=4.0.1) ; extra == 'dev'
Requires-Dist: isort (>=5.10.1) ; extra == 'dev'
Requires-Dist: tox (>=3.25.0) ; extra == 'dev'
Provides-Extra: lint
Requires-Dist: flake8 (>=4.0.1) ; extra == 'lint'
Requires-Dist: isort (>=5.10.1) ; extra == 'lint'
Provides-Extra: test
Requires-Dist: pytest (>=7.0.0) ; extra == 'test'
Requires-Dist: pytest-cov (>=3.0.0) ; extra == 'test'
